[
  {
    "alpha3Code": "ABW",
    "capital": "Oranjestad",
    "name": "Aruba",
    "region": "Americas",
    "subregion": "Caribbean"
  },
  {
    "alpha3Code": "AFG",
    "capital": "Kabul",
    "name": "Afghanistan",
    "region": "Asia",
    "subregion": "Southern Asia"
  },
  {
    "alpha3Code": "AGO",
    "capital": "Luanda",
    "name": "Angola",
    "region": "Africa",
    "subregion": "Middle Africa"
  },
  {
    "alpha3Code": "AIA",
    "capital": "The Valley",
    "name": "Anguilla",
    "region": "Americas",
    "subregion": "Caribbean"
  },
  {
    "alpha3Code": "ALA",
    "capital": "Mariehamn",
    "name": "Åland Islands",
    "region": "Europe",
    "subregion": "Northern Europe"
  },
  {
    "alpha3Code": "ALB",
    "capital": "Tirana",
    "name": "Albania",
    "region": "Europe",
    "subregion": "Southern Europe"
  },
  {
    "alpha3Code": "AND",
    "capital": "Andorra la Vella",
    "name": "Andorra",
    "region": "Europe",
    "subregion": "Southern Europe"
  },
  {
    "alpha3Code": "ARE",
    "capital": "Abu Dhabi",
    "name": "United Arab Emirates",
    "region": "Asia",
    "subregion": "Western Asia"
  },
  {
    "alpha3Code": "ARG",
    "capital": "Buenos Aires",
    "name": "Argentina",
    "region": "Americas",
    "subregion": "South America"
  },
  {
    "alpha3Code": "ARM",
    "capital": "Yerevan",
    "name": "Armenia",
    "region": "Asia",
    "subregion": "Western Asia"
  },
  {
    "alpha3Code": "ASM",
    "capital": "Pago Pago",
    "name": "American Samoa",
    "region": "Oceania",
    "subregion": "Polynesia"
  },
  {
    "alpha3Code": "ATA",
    "capital": "",
    "name": "Antarctica",
    "region": "Polar",
    "subregion": ""
  },
  {
    "alpha3Code": "ATF",
    "capital": "Port-aux-Français",
    "name": "French Southern Territories",
    "region": "Africa",
    "subregion": "Southern Africa"
  },
  {
    "alpha3Code": "ATG",
    "capital": "Saint John's",
    "name": "Antigua and Barbuda",
    "region": "Americas",
    "subregion": "Caribbean"
  },
  {
    "alpha3Code": "AUS",
    "capital": "Canberra",
    "name": "Australia",
    "region": "Oceania",
    "subregion": "Australia and New Zealand"
  },
  {
    "alpha3Code": "AUT",
    "capital": "Vienna",
    "name": "Austria",
    "region": "Europe",
    "subregion": "Western Europe"
  },
  {
    "alpha3Code": "AZE",
    "capital": "Baku",
    "name": "Azerbaijan",
    "region": "Asia",
    "subregion": "Western Asia"
  },
  {
    "alpha3Code": "BDI",
    "capital": "Gitega",
    "name": "Burundi",
    "region": "Africa",
    "subregion": "Eastern Africa"
  },
  {
    "alpha3Code": "BEL",
    "capital": "Brussels",
    "name": "Belgium",
    "region": "Europe",
    "subregion": "Western Europe"
  },
  {
    "alpha3Code": "BEN",
    "capital": "Porto-Novo",
    "name": "Benin",
    "region": "Africa",
    "subregion": "Western Africa"
  },
  {
    "alpha3Code": "BES",
    "capital": "Kralendijk",
    "name": "Bonaire, Sint Eustatius and Saba",
    "region": "Americas",
    "subregion": "Caribbean"
  },
  {
    "alpha3Code": "BFA",
    "capital": "Ouagadougou",
    "name": "Burkina Faso",
    "region": "Africa",
    "subregion": "Western Africa"
  },
  {
    "alpha3Code": "BGD",
    "capital": "Dhaka",
    "name": "Bangladesh",
    "region": "Asia",
    "subregion": "Southern Asia"
  },
  {
    "alpha3Code": "BGR",
    "capital": "Sofia",
    "name": "Bulgaria",
    "region": "Europe",
    "subregion": "Eastern Europe"
  },
  {
    "alpha3Code": "BHR",
    "capital": "Manama",
    "name": "Bahrain",
    "region": "Asia",
    "subregion": "Western Asia"
  },
  {
    "alpha3Code": "BHS",
    "capital": "Nassau",
    "name": "Bahamas",
    "region": "Americas",
    "subregion": "Caribbean"
  },
  {
    "alpha3Code": "BIH",
    "capital": "Sarajevo",
    "name": "Bosnia and Herzegovina",
    "region": "Europe",
    "subregion": "Southern Europe"
  },
  {
    "alpha3Code": "BLM",
    "capital": "Gustavia",
    "name": "Saint Barthélemy",
    "region": "Americas",
    "subregion": "Caribbean"
  },
  {
    "alpha3Code": "BLR",
    "capital": "Minsk",
    "name": "Belarus",
    "region": "Europe",
    "subregion": "Eastern Europe"
  },
  {
    "alpha3Code": "BLZ",
    "capital": "Belmopan",
    "name": "Belize",
    "region": "Americas",
    "subregion": "Central America"
  },
  {
    "alpha3Code": "BMU",
    "capital": "Hamilton",
    "name": "Bermuda",
    "region": "Americas",
    "subregion": "Northern America"
  },
  {
    "alpha3Code": "BOL",
    "capital": "Sucre",
    "name": "Bolivia (Plurinational State of)",
    "region": "Americas",
    "subregion": "South America"
  },
  {
    "alpha3Code": "BRA",
    "capital": "Brasília",
    "name": "Brazil",
    "region": "Americas",
    "subregion": "South America"
  },
  {
    "alpha3Code": "BRB",
    "capital": "Bridgetown",
    "name": "Barbados",
    "region": "Americas",
    "subregion": "Caribbean"
  },
  {
    "alpha3Code": "BRN",
    "capital": "Bandar Seri Begawan",
    "name": "Brunei Darussalam",
    "region": "Asia",
    "subregion": "South-Eastern Asia"
  },
  {
    "alpha3Code": "BTN",
    "capital": "Thimphu",
    "name": "Bhutan",
    "region": "Asia",
    "subregion": "Southern Asia"
  },
  {
    "alpha3Code": "BVT",
    "capital": "",
    "name": "Bouvet Island",
    "region": "Polar",
    "subregion": ""
  },
  {
    "alpha3Code": "BWA",
    "capital": "Gaborone",
    "name": "Botswana",
    "region": "Africa",
    "subregion": "Southern Africa"
  },
  {
    "alpha3Code": "CAF",
    "capital": "Bangui",
    "name": "Central African Republic",
    "region": "Africa",
    "subregion": "Middle Africa"
  },
  {
    "alpha3Code": "CAN",
    "capital": "Ottawa",
    "name": "Canada",
    "region": "Americas",
    "subregion": "Northern America"
  },
  {
    "alpha3Code": "CCK",
    "capital": "West Island",
    "name": "Cocos (Keeling) Islands",
    "region": "Oceania",
    "subregion": "Australia and New Zealand"
  },
  {
    "alpha3Code": "CHE",
    "capital": "Bern",
    "name": "Switzerland",
    "region": "Europe",
    "subregion": "Western Europe"
  },
  {
    "alpha3Code": "CHL",
    "capital": "Santiago",
    "name": "Chile",
    "region": "Americas",
    "subregion": "South America"
  },
  {
    "alpha3Code": "CHN",
    "capital": "Beijing",
    "name": "China",
    "region": "Asia",
    "subregion": "Eastern Asia"
  },
  {
    "alpha3Code": "CIV",
    "capital": "Yamoussoukro",
    "name": "Côte d'Ivoire",
    "region": "Africa",
    "subregion": "Western Africa"
  },
  {
    "alpha3Code": "CMR",
    "capital": "Yaoundé",
    "name": "Cameroon",
    "region": "Africa",
    "subregion": "Middle Africa"
  },
  {
    "alpha3Code": "COD",
    "capital": "Kinshasa",
    "name": "Congo (Democratic Republic of the)",
    "region": "Africa",
    "subregion": "Middle Africa"
  },
  {
    "alpha3Code": "COG",
    "capital": "Brazzaville",
    "name": "Congo",
    "region": "Africa",
    "subregion": "Middle Africa"
  },
  {
    "alpha3Code": "COK",
    "capital": "Avarua",
    "name": "Cook Islands",
    "region": "Oceania",
    "subregion": "Polynesia"
  },
  {
    "alpha3Code": "COL",
    "capital": "Bogotá",
    "name": "Colombia",
    "region": "Americas",
    "subregion": "South America"
  },
  {
    "alpha3Code": "COM",
    "capital": "Moroni",
    "name": "Comoros",
    "region": "Africa",
    "subregion": "Eastern Africa"
  },
  {
    "alpha3Code": "CPV",
    "capital": "Praia",
    "name": "Cabo Verde",
    "region": "Africa",
    "subregion": "Western Africa"
  },
  {
    "alpha3Code": "CRI",
    "capital": "San José",
    "name": "Costa Rica",
    "region": "Americas",
    "subregion": "Central America"
  },
  {
    "alpha3Code": "CUB",
    "capital": "Havana",
    "name": "Cuba",
    "region": "Americas",
    "subregion": "Caribbean"
  },
  {
    "alpha3Code": "CUW",
    "capital": "Willemstad",
    "name": "Curaçao",
    "region": "Americas",
    "subregion": "Caribbean"
  },
  {
    "alpha3Code": "CXR",
    "capital": "Flying Fish Cove",
    "name": "Christmas Island",
    "region": "Oceania",
    "subregion": "Australia and New Zealand"
  },
  {
    "alpha3Code": "CYM",
    "capital": "George Town",
    "name": "Cayman Islands",
    "region": "Americas",
    "subregion": "Caribbean"
  },
  {
    "alpha3Code": "CYP",
    "capital": "Nicosia",
    "name": "Cyprus",
    "region": "Europe",
    "subregion": "Southern Europe"
  },
  {
    "alpha3Code": "CZE",
    "capital": "Prague",
    "name": "Czech Republic",
    "region": "Europe",
    "subregion": "Eastern Europe"
  },
  {
    "alpha3Code": "DEU",
    "capital": "Berlin",
    "name": "Germany",
    "region": "Europe",
    "subregion": "Western Europe"
  },
  {
    "alpha3Code": "DJI",
    "capital": "Djibouti",
    "name": "Djibouti",
    "region": "Africa",
    "subregion": "Eastern Africa"
  },
  {
    "alpha3Code": "DMA",
    "capital": "Roseau",
    "name": "Dominica",
    "region": "Americas",
    "subregion": "Caribbean"
  },
  {
    "alpha3Code": "DNK",
    "capital": "Copenhagen",
    "name": "Denmark",
    "region": "Europe",
    "subregion": "Northern Europe"
  },
  {
    "alpha3Code": "DOM",
    "capital": "Santo Domingo",
    "name": "Dominican Republic",
    "region": "Americas",
    "subregion": "Caribbean"
  },
  {
    "alpha3Code": "DZA",
    "capital": "Algiers",
    "name": "Algeria",
    "region": "Africa",
    "subregion": "Northern Africa"
  },
  {
    "alpha3Code": "ECU",
    "capital": "Quito",
    "name": "Ecuador",
    "region": "Americas",
    "subregion": "South America"
  },
  {
    "alpha3Code": "EGY",
    "capital": "Cairo",
    "name": "Egypt",
    "region": "Africa",
    "subregion": "Northern Africa"
  },
  {
    "alpha3Code": "ERI",
    "capital": "Asmara",
    "name": "Eritrea",
    "region": "Africa",
    "subregion": "Eastern Africa"
  },
  {
    "alpha3Code": "ESH",
    "capital": "El Aaiún",
    "name": "Western Sahara",
    "region": "Africa",
    "subregion": "Northern Africa"
  },
  {
    "alpha3Code": "ESP",
    "capital": "Madrid",
    "name": "Spain",
    "region": "Europe",
    "subregion": "Southern Europe"
  },
  {
    "alpha3Code": "EST",
    "capital": "Tallinn",
    "name": "Estonia",
    "region": "Europe",
    "subregion": "Northern Europe"
  },
  {
    "alpha3Code": "ETH",
    "capital": "Addis Ababa",
    "name": "Ethiopia",
    "region": "Africa",
    "subregion": "Eastern Africa"
  },
  {
    "alpha3Code": "FIN",
    "capital": "Helsinki",
    "name": "Finland",
    "region": "Europe",
    "subregion": "Northern Europe"
  },
  {
    "alpha3Code": "FJI",
    "capital": "Suva",
    "name": "Fiji",
    "region": "Oceania",
    "subregion": "Melanesia"
  },
  {
    "alpha3Code": "FLK",
    "capital": "Stanley",
    "name": "Falkland Islands (Malvinas)",
    "region": "Americas",
    "subregion": "South America"
  },
  {
    "alpha3Code": "FRA",
    "capital": "Paris",
    "name": "France",
    "region": "Europe",
    "subregion": "Western Europe"
  },
  {
    "alpha3Code": "FRO",
    "capital": "Tórshavn",
    "name": "Faroe Islands",
    "region": "Europe",
    "subregion": "Northern Europe"
  },
  {
    "alpha3Code": "FSM",
    "capital": "Palikir",
    "name": "Micronesia (Federated States of)",
    "region": "Oceania",
    "subregion": "Micronesia"
  },
  {
    "alpha3Code": "GAB",
    "capital": "Libreville",
    "name": "Gabon",
    "region": "Africa",
    "subregion": "Middle Africa"
  },
  {
    "alpha3Code": "GBR",
    "capital": "London",
    "name": "United Kingdom of Great Britain and Northern Ireland",
    "region": "Europe",
    "subregion": "Northern Europe"
  },
  {
    "alpha3Code": "GEO",
    "capital": "Tbilisi",
    "name": "Georgia",
    "region": "Asia",
    "subregion": "Western Asia"
  },
  {
    "alpha3Code": "GGY",
    "capital": "St. Peter Port",
    "name": "Guernsey",
    "region": "Europe",
    "subregion": "Northern Europe"
  },
  {
    "alpha3Code": "GHA",
    "capital": "Accra",
    "name": "Ghana",
    "region": "Africa",
    "subregion": "Western Africa"
  },
  {
    "alpha3Code": "GIB",
    "capital": "Gibraltar",
    "name": "Gibraltar",
    "region": "Europe",
    "subregion": "Southern Europe"
  },
  {
    "alpha3Code": "GIN",
    "capital": "Conakry",
    "name": "Guinea",
    "region": "Africa",
    "subregion": "Western Africa"
  },
  {
    "alpha3Code": "GLP",
    "capital": "Basse-Terre",
    "name": "Guadeloupe",
    "region": "Americas",
    "subregion": "Caribbean"
  },
  {
    "alpha3Code": "GMB",
    "capital": "Banjul",
    "name": "Gambia",
    "region": "Africa",
    "subregion": "Western Africa"
  },
  {
    "alpha3Code": "GNB",
    "capital": "Bissau",
    "name": "Guinea-Bissau",
    "region": "Africa",
    "subregion": "Western Africa"
  },
  {
    "alpha3Code": "GNQ",
    "capital": "Malabo",
    "name": "Equatorial Guinea",
    "region": "Africa",
    "subregion": "Middle Africa"
  },
  {
    "alpha3Code": "GRC",
    "capital": "Athens",
    "name": "Greece",
    "region": "Europe",
    "subregion": "Southern Europe"
  },
  {
    "alpha3Code": "GRD",
    "capital": "St. George's",
    "name": "Grenada",
    "region": "Americas",
    "subregion": "Caribbean"
  },
  {
    "alpha3Code": "GRL",
    "capital": "Nuuk",
    "name": "Greenland",
    "region": "Americas",
    "subregion": "Northern America"
  },
  {
    "alpha3Code": "GTM",
    "capital": "Guatemala City",
    "name": "Guatemala",
    "region": "Americas",
    "subregion": "Central America"
  },
  {
    "alpha3Code": "GUF",
    "capital": "Cayenne",
    "name": "French Guiana",
    "region": "Americas",
    "subregion": "South America"
  },
  {
    "alpha3Code": "GUM",
    "capital": "Hagåtña",
    "name": "Guam",
    "region": "Oceania",
    "subregion": "Micronesia"
  },
  {
    "alpha3Code": "GUY",
    "capital": "Georgetown",
    "name": "Guyana",
    "region": "Americas",
    "subregion": "South America"
  },
  {
    "alpha3Code": "HKG",
    "capital": "City of Victoria",
    "name": "Hong Kong",
    "region": "Asia",
    "subregion": "Eastern Asia"
  },
  {
    "alpha3Code": "HMD",
    "capital": "",
    "name": "Heard Island and McDonald Islands",
    "region": "Polar",
    "subregion": ""
  },
  {
    "alpha3Code": "HND",
    "capital": "Tegucigalpa",
    "name": "Honduras",
    "region": "Americas",
    "subregion": "Central America"
  },
  {
    "alpha3Code": "HRV",
    "capital": "Zagreb",
    "name": "Croatia",
    "region": "Europe",
    "subregion": "Southern Europe"
  },
  {
    "alpha3Code": "HTI",
    "capital": "Port-au-Prince",
    "name": "Haiti",
    "region": "Americas",
    "subregion": "Caribbean"
  },
  {
    "alpha3Code": "HUN",
    "capital": "Budapest",
    "name": "Hungary",
    "region": "Europe",
    "subregion": "Eastern Europe"
  },
  {
    "alpha3Code": "IDN",
    "capital": "Jakarta",
    "name": "Indonesia",
    "region": "Asia",
    "subregion": "South-Eastern Asia"
  },
  {
    "alpha3Code": "IMN",
    "capital": "Douglas",
    "name": "Isle of Man",
    "region": "Europe",
    "subregion": "Northern Europe"
  },
  {
    "alpha3Code": "IND",
    "capital": "New Delhi",
    "name": "India",
    "region": "Asia",
    "subregion": "Southern Asia"
  },
  {
    "alpha3Code": "IOT",
    "capital": "Diego Garcia",
    "name": "British Indian Ocean Territory",
    "region": "Africa",
    "subregion": "Eastern Africa"
  },
  {
    "alpha3Code": "IRL",
    "capital": "Dublin",
    "name": "Ireland",
    "region": "Europe",
    "subregion": "Northern Europe"
  },
  {
    "alpha3Code": "IRN",
    "capital": "Tehran",
    "name": "Iran (Islamic Republic of)",
    "region": "Asia",
    "subregion": "Southern Asia"
  },
  {
    "alpha3Code": "IRQ",
    "capital": "Baghdad",
    "name": "Iraq",
    "region": "Asia",
    "subregion": "Western Asia"
  },
  {
    "alpha3Code": "ISL",
    "capital": "Reykjavík",
    "name": "Iceland",
    "region": "Europe",
    "subregion": "Northern Europe"
  },
  {
    "alpha3Code": "ISR",
    "capital": "Jerusalem",
    "name": "Israel",
    "region": "Asia",
    "subregion": "Western Asia"
  },
  {
    "alpha3Code": "ITA",
    "capital": "Rome",
    "name": "Italy",
    "region": "Europe",
    "subregion": "Southern Europe"
  },
  {
    "alpha3Code": "JAM",
    "capital": "Kingston",
    "name": "Jamaica",
    "region": "Americas",
    "subregion": "Caribbean"
  },
  {
    "alpha3Code": "JEY",
    "capital": "Saint Helier",
    "name": "Jersey",
    "region": "Europe",
    "subregion": "Northern Europe"
  },
  {
    "alpha3Code": "JOR",
    "capital": "Amman",
    "name": "Jordan",
    "region": "Asia",
    "subregion": "Western Asia"
  },
  {
    "alpha3Code": "JPN",
    "capital": "Tokyo",
    "name": "Japan",
    "region": "Asia",
    "subregion": "Eastern Asia"
  },
  {
    "alpha3Code": "KAZ",
    "capital": "Nur-Sultan",
    "name": "Kazakhstan",
    "region": "Asia",
    "subregion": "Central Asia"
  },
  {
    "alpha3Code": "KEN",
    "capital": "Nairobi",
    "name": "Kenya",
    "region": "Africa",
    "subregion": "Eastern Africa"
  },
  {
    "alpha3Code": "KGZ",
    "capital": "Bishkek",
    "name": "Kyrgyzstan",
    "region": "Asia",
    "subregion": "Central Asia"
  },
  {
    "alpha3Code": "KHM",
    "capital": "Phnom Penh",
    "name": "Cambodia",
    "region": "Asia",
    "subregion": "South-Eastern Asia"
  },
  {
    "alpha3Code": "KIR",
    "capital": "South Tarawa",
    "name": "Kiribati",
    "region": "Oceania",
    "subregion": "Micronesia"
  },
  {
    "alpha3Code": "KNA",
    "capital": "Basseterre",
    "name": "Saint Kitts and Nevis",
    "region": "Americas",
    "subregion": "Caribbean"
  },
  {
    "alpha3Code": "KOR",
    "capital": "Seoul",
    "name": "Korea (Republic of)",
    "region": "Asia",
    "subregion": "Eastern Asia"
  },
  {
    "alpha3Code": "KWT",
    "capital": "Kuwait City",
    "name": "Kuwait",
    "region": "Asia",
    "subregion": "Western Asia"
  },
  {
    "alpha3Code": "LAO",
    "capital": "Vientiane",
    "name": "Lao People's Democratic Republic",
    "region": "Asia",
    "subregion": "South-Eastern Asia"
  },
  {
    "alpha3Code": "LBN",
    "capital": "Beirut",
    "name": "Lebanon",
    "region": "Asia",
    "subregion": "Western Asia"
  },
  {
    "alpha3Code": "LBR",
    "capital": "Monrovia",
    "name": "Liberia",
    "region": "Africa",
    "subregion": "Western Africa"
  },
  {
    "alpha3Code": "LBY",
    "capital": "Tripoli",
    "name": "Libya",
    "region": "Africa",
    "subregion": "Northern Africa"
  },
  {
    "alpha3Code": "LCA",
    "capital": "Castries",
    "name": "Saint Lucia",
    "region": "Americas",
    "subregion": "Caribbean"
  },
  {
    "alpha3Code": "LIE",
    "capital": "Vaduz",
    "name": "Liechtenstein",
    "region": "Europe",
    "subregion": "Western Europe"
  },
  {
    "alpha3Code": "LKA",
    "capital": "Sri Jayawardenepura Kotte",
    "name": "Sri Lanka",
    "region": "Asia",
    "subregion": "Southern Asia"
  },
  {
    "alpha3Code": "LSO",
    "capital": "Maseru",
    "name": "Lesotho",
    "region": "Africa",
    "subregion": "Southern Africa"
  },
  {
    "alpha3Code": "LTU",
    "capital": "Vilnius",
    "name": "Lithuania",
    "region": "Europe",
    "subregion": "Northern Europe"
  },
  {
    "alpha3Code": "LUX",
    "capital": "Luxembourg",
    "name": "Luxembourg",
    "region": "Europe",
    "subregion": "Western Europe"
  },
  {
    "alpha3Code": "LVA",
    "capital": "Riga",
    "name": "Latvia",
    "region": "Europe",
    "subregion": "Northern Europe"
  },
  {
    "alpha3Code": "MAC",
    "capital": "",
    "name": "Macao",
    "region": "Asia",
    "subregion": "Eastern Asia"
  },
  {
    "alpha3Code": "MAF",
    "capital": "Marigot",
    "name": "Saint Martin (French part)",
    "region": "Americas",
    "subregion": "Caribbean"
  },
  {
    "alpha3Code": "MAR",
    "capital": "Rabat",
    "name": "Morocco",
    "region": "Africa",
    "subregion": "Northern Africa"
  },
  {
    "alpha3Code": "MCO",
    "capital": "Monaco",
    "name": "Monaco",
    "region": "Europe",
    "subregion": "Western Europe"
  },
  {
    "alpha3Code": "MDA",
    "capital": "Chișinău",
    "name": "Moldova (Republic of)",
    "region": "Europe",
    "subregion": "Eastern Europe"
  },
  {
    "alpha3Code": "MDG",
    "capital": "Antananarivo",
    "name": "Madagascar",
    "region": "Africa",
    "subregion": "Eastern Africa"
  },
  {
    "alpha3Code": "MDV",
    "capital": "Malé",
    "name": "Maldives",
    "region": "Asia",
    "subregion": "Southern Asia"
  },
  {
    "alpha3Code": "MEX",
    "capital": "Mexico City",
    "name": "Mexico",
    "region": "Americas",
    "subregion": "Central America"
  },
  {
    "alpha3Code": "MHL",
    "capital": "Majuro",
    "name": "Marshall Islands",
    "region": "Oceania",
    "subregion": "Micronesia"
  },
  {
    "alpha3Code": "MKD",
    "capital": "Skopje",
    "name": "North Macedonia",
    "region": "Europe",
    "subregion": "Southern Europe"
  },
  {
    "alpha3Code": "MLI",
    "capital": "Bamako",
    "name": "Mali",
    "region": "Africa",
    "subregion": "Western Africa"
  },
  {
    "alpha3Code": "MLT",
    "capital": "Valletta",
    "name": "Malta",
    "region": "Europe",
    "subregion": "Southern Europe"
  },
  {
    "alpha3Code": "MMR",
    "capital": "Naypyidaw",
    "name": "Myanmar",
    "region": "Asia",
    "subregion": "South-Eastern Asia"
  },
  {
    "alpha3Code": "MNE",
    "capital": "Podgorica",
    "name": "Montenegro",
    "region": "Europe",
    "subregion": "Southern Europe"
  },
  {
    "alpha3Code": "MNG",
    "capital": "Ulan Bator",
    "name": "Mongolia",
    "region": "Asia",
    "subregion": "Eastern Asia"
  },
  {
    "alpha3Code": "MNP",
    "capital": "Saipan",
    "name": "Northern Mariana Islands",
    "region": "Oceania",
    "subregion": "Micronesia"
  },
  {
    "alpha3Code": "MOZ",
    "capital": "Maputo",
    "name": "Mozambique",
    "region": "Africa",
    "subregion": "Eastern Africa"
  },
  {
    "alpha3Code": "MRT",
    "capital": "Nouakchott",
    "name": "Mauritania",
    "region": "Africa",
    "subregion": "Western Africa"
  },
  {
    "alpha3Code": "MSR",
    "capital": "Plymouth",
    "name": "Montserrat",
    "region": "Americas",
    "subregion": "Caribbean"
  },
  {
    "alpha3Code": "MTQ",
    "capital": "Fort-de-France",
    "name": "Martinique",
    "region": "Americas",
    "subregion": "Caribbean"
  },
  {
    "alpha3Code": "MUS",
    "capital": "Port Louis",
    "name": "Mauritius",
    "region": "Africa",
    "subregion": "Eastern Africa"
  },
  {
    "alpha3Code": "MWI",
    "capital": "Lilongwe",
    "name": "Malawi",
    "region": "Africa",
    "subregion": "Eastern Africa"
  },
  {
    "alpha3Code": "MYS",
    "capital": "Kuala Lumpur",
    "name": "Malaysia",
    "region": "Asia",
    "subregion": "South-Eastern Asia"
  },
  {
    "alpha3Code": "MYT",
    "capital": "Mamoudzou",
    "name": "Mayotte",
    "region": "Africa",
    "subregion": "Eastern Africa"
  },
  {
    "alpha3Code": "NAM",
    "capital": "Windhoek",
    "name": "Namibia",
    "region": "Africa",
    "subregion": "Southern Africa"
  },
  {
    "alpha3Code": "NCL",
    "capital": "Nouméa",
    "name": "New Caledonia",
    "region": "Oceania",
    "subregion": "Melanesia"
  },
  {
    "alpha3Code": "NER",
    "capital": "Niamey",
    "name": "Niger",
    "region": "Africa",
    "subregion": "Western Africa"
  },
  {
    "alpha3Code": "NFK",
    "capital": "Kingston",
    "name": "Norfolk Island",
    "region": "Oceania",
    "subregion": "Australia and New Zealand"
  },
  {
    "alpha3Code": "NGA",
    "capital": "Abuja",
    "name": "Nigeria",
    "region": "Africa",
    "subregion": "Western Africa"
  },
  {
    "alpha3Code": "NIC",
    "capital": "Managua",
    "name": "Nicaragua",
    "region": "Americas",
    "subregion": "Central America"
  },
  {
    "alpha3Code": "NIU",
    "capital": "Alofi",
    "name": "Niue",
    "region": "Oceania",
    "subregion": "Polynesia"
  },
  {
    "alpha3Code": "NLD",
    "capital": "Amsterdam",
    "name": "Netherlands",
    "region": "Europe",
    "subregion": "Western Europe"
  },
  {
    "alpha3Code": "NOR",
    "capital": "Oslo",
    "name": "Norway",
    "region": "Europe",
    "subregion": "Northern Europe"
  },
  {
    "alpha3Code": "NPL",
    "capital": "Kathmandu",
    "name": "Nepal",
    "region": "Asia",
    "subregion": "Southern Asia"
  },
  {
    "alpha3Code": "NRU",
    "capital": "Yaren",
    "name": "Nauru",
    "region": "Oceania",
    "subregion": "Micronesia"
  },
  {
    "alpha3Code": "NZL",
    "capital": "Wellington",
    "name": "New Zealand",
    "region": "Oceania",
    "subregion": "Australia and New Zealand"
  },
  {
    "alpha3Code": "OMN",
    "capital": "Muscat",
    "name": "Oman",
    "region": "Asia",
    "subregion": "Western Asia"
  },
  {
    "alpha3Code": "PAK",
    "capital": "Islamabad",
    "name": "Pakistan",
    "region": "Asia",
    "subregion": "Southern Asia"
  },
  {
    "alpha3Code": "PAN",
    "capital": "Panama City",
    "name": "Panama",
    "region": "Americas",
    "subregion": "Central America"
  },
  {
    "alpha3Code": "PCN",
    "capital": "Adamstown",
    "name": "Pitcairn",
    "region": "Oceania",
    "subregion": "Polynesia"
  },
  {
    "alpha3Code": "PER",
    "capital": "Lima",
    "name": "Peru",
    "region": "Americas",
    "subregion": "South America"
  },
  {
    "alpha3Code": "PHL",
    "capital": "Manila",
    "name": "Philippines",
    "region": "Asia",
    "subregion": "South-Eastern Asia"
  },
  {
    "alpha3Code": "PLW",
    "capital": "Ngerulmud",
    "name": "Palau",
    "region": "Oceania",
    "subregion": "Micronesia"
  },
  {
    "alpha3Code": "PNG",
    "capital": "Port Moresby",
    "name": "Papua New Guinea",
    "region": "Oceania",
    "subregion": "Melanesia"
  },
  {
    "alpha3Code": "POL",
    "capital": "Warsaw",
    "name": "Poland",
    "region": "Europe",
    "subregion": "Eastern Europe"
  },
  {
    "alpha3Code": "PRI",
    "capital": "San Juan",
    "name": "Puerto Rico",
    "region": "Americas",
    "subregion": "Caribbean"
  },
  {
    "alpha3Code": "PRK",
    "capital": "Pyongyang",
    "name": "Korea (Democratic People's Republic of)",
    "region": "Asia",
    "subregion": "Eastern Asia"
  },
  {
    "alpha3Code": "PRT",
    "capital": "Lisbon",
    "name": "Portugal",
    "region": "Europe",
    "subregion": "Southern Europe"
  },
  {
    "alpha3Code": "PRY",
    "capital": "Asunción",
    "name": "Paraguay",
    "region": "Americas",
    "subregion": "South America"
  },
  {
    "alpha3Code": "PSE",
    "capital": "Ramallah",
    "name": "Palestine, State of Palestine",
    "region": "Asia",
    "subregion": "Western Asia"
  },
  {
    "alpha3Code": "PYF",
    "capital": "Papeetē",
    "name": "French Polynesia",
    "region": "Oceania",
    "subregion": "Polynesia"
  },
  {
    "alpha3Code": "QAT",
    "capital": "Doha",
    "name": "Qatar",
    "region": "Asia",
    "subregion": "Western Asia"
  },
  {
    "alpha3Code": "REU",
    "capital": "Saint-Denis",
    "name": "Réunion",
    "region": "Africa",
    "subregion": "Eastern Africa"
  },
  {
    "alpha3Code": "ROU",
    "capital": "Bucharest",
    "name": "Romania",
    "region": "Europe",
    "subregion": "Eastern Europe"
  },
  {
    "alpha3Code": "RUS",
    "capital": "Moscow",
    "name": "Russian Federation",
    "region": "Europe",
    "subregion": "Eastern Europe"
  },
  {
    "alpha3Code": "RWA",
    "capital": "Kigali",
    "name": "Rwanda",
    "region": "Africa",
    "subregion": "Eastern Africa"
  },
  {
    "alpha3Code": "SAU",
    "capital": "Riyadh",
    "name": "Saudi Arabia",
    "region": "Asia",
    "subregion": "Western Asia"
  },
  {
    "alpha3Code": "SDN",
    "capital": "Khartoum",
    "name": "Sudan",
    "region": "Africa",
    "subregion": "Northern Africa"
  },
  {
    "alpha3Code": "SEN",
    "capital": "Dakar",
    "name": "Senegal",
    "region": "Africa",
    "subregion": "Western Africa"
  },
  {
    "alpha3Code": "SGP",
    "capital": "Singapore",
    "name": "Singapore",
    "region": "Asia",
    "subregion": "South-Eastern Asia"
  },
  {
    "alpha3Code": "SGS",
    "capital": "King Edward Point",
    "name": "South Georgia and the South Sandwich Islands",
    "region": "Americas",
    "subregion": "South America"
  },
  {
    "alpha3Code": "SHN",
    "capital": "Jamestown",
    "name": "Saint Helena, Ascension and Tristan da Cunha",
    "region": "Africa",
    "subregion": "Western Africa"
  },
  {
    "alpha3Code": "SJM",
    "capital": "Longyearbyen",
    "name": "Svalbard and Jan Mayen",
    "region": "Europe",
    "subregion": "Northern Europe"
  },
  {
    "alpha3Code": "SLB",
    "capital": "Honiara",
    "name": "Solomon Islands",
    "region": "Oceania",
    "subregion": "Melanesia"
  },
  {
    "alpha3Code": "SLE",
    "capital": "Freetown",
    "name": "Sierra Leone",
    "region": "Africa",
    "subregion": "Western Africa"
  },
  {
    "alpha3Code": "SLV",
    "capital": "San Salvador",
    "name": "El Salvador",
    "region": "Americas",
    "subregion": "Central America"
  },
  {
    "alpha3Code": "SMR",
    "capital": "City of San Marino",
    "name": "San Marino",
    "region": "Europe",
    "subregion": "Southern Europe"
  },
  {
    "alpha3Code": "SOM",
    "capital": "Mogadishu",
    "name": "Somalia",
    "region": "Africa",
    "subregion": "Eastern Africa"
  },
  {
    "alpha3Code": "SPM",
    "capital": "Saint-Pierre",
    "name": "Saint Pierre and Miquelon",
    "region": "Americas",
    "subregion": "Northern America"
  },
  {
    "alpha3Code": "SRB",
    "capital": "Belgrade",
    "name": "Serbia",
    "region": "Europe",
    "subregion": "Southern Europe"
  },
  {
    "alpha3Code": "SSD",
    "capital": "Juba",
    "name": "South Sudan",
    "region": "Africa",
    "subregion": "Middle Africa"
  },
  {
    "alpha3Code": "STP",
    "capital": "São Tomé",
    "name": "Sao Tome and Principe",
    "region": "Africa",
    "subregion": "Middle Africa"
  },
  {
    "alpha3Code": "SUR",
    "capital": "Paramaribo",
    "name": "Suriname",
    "region": "Americas",
    "subregion": "South America"
  },
  {
    "alpha3Code": "SVK",
    "capital": "Bratislava",
    "name": "Slovakia",
    "region": "Europe",
    "subregion": "Eastern Europe"
  },
  {
    "alpha3Code": "SVN",
    "capital": "Ljubljana",
    "name": "Slovenia",
    "region": "Europe",
    "subregion": "Southern Europe"
  },
  {
    "alpha3Code": "SWE",
    "capital": "Stockholm",
    "name": "Sweden",
    "region": "Europe",
    "subregion": "Northern Europe"
  },
  {
    "alpha3Code": "SWZ",
    "capital": "Mbabane",
    "name": "Eswatini",
    "region": "Africa",
    "subregion": "Southern Africa"
  },
  {
    "alpha3Code": "SXM",
    "capital": "Philipsburg",
    "name": "Sint Maarten (Dutch part)",
    "region": "Americas",
    "subregion": "Caribbean"
  },
  {
    "alpha3Code": "SYC",
    "capital": "Victoria",
    "name": "Seychelles",
    "region": "Africa",
    "subregion": "Eastern Africa"
  },
  {
    "alpha3Code": "SYR",
    "capital": "Damascus",
    "name": "Syrian Arab Republic",
    "region": "Asia",
    "subregion": "Western Asia"
  },
  {
    "alpha3Code": "TCA",
    "capital": "Cockburn Town",
    "name": "Turks and Caicos Islands",
    "region": "Americas",
    "subregion": "Caribbean"
  },
  {
    "alpha3Code": "TCD",
    "capital": "N'Djamena",
    "name": "Chad",
    "region": "Africa",
    "subregion": "Middle Africa"
  },
  {
    "alpha3Code": "TGO",
    "capital": "Lomé",
    "name": "Togo",
    "region": "Africa",
    "subregion": "Western Africa"
  },
  {
    "alpha3Code": "THA",
    "capital": "Bangkok",
    "name": "Thailand",
    "region": "Asia",
    "subregion": "South-Eastern Asia"
  },
  {
    "alpha3Code": "TJK",
    "capital": "Dushanbe",
    "name": "Tajikistan",
    "region": "Asia",
    "subregion": "Central Asia"
  },
  {
    "alpha3Code": "TKL",
    "capital": "Fakaofo",
    "name": "Tokelau",
    "region": "Oceania",
    "subregion": "Polynesia"
  },
  {
    "alpha3Code": "TKM",
    "capital": "Ashgabat",
    "name": "Turkmenistan",
    "region": "Asia",
    "subregion": "Central Asia"
  },
  {
    "alpha3Code": "TLS",
    "capital": "Dili",
    "name": "Timor-Leste",
    "region": "Asia",
    "subregion": "South-Eastern Asia"
  },
  {
    "alpha3Code": "TON",
    "capital": "Nuku'alofa",
    "name": "Tonga",
    "region": "Oceania",
    "subregion": "Polynesia"
  },
  {
    "alpha3Code": "TTO",
    "capital": "Port of Spain",
    "name": "Trinidad and Tobago",
    "region": "Americas",
    "subregion": "Caribbean"
  },
  {
    "alpha3Code": "TUN",
    "capital": "Tunis",
    "name": "Tunisia",
    "region": "Africa",
    "subregion": "Northern Africa"
  },
  {
    "alpha3Code": "TUR",
    "capital": "Ankara",
    "name": "Turkey",
    "region": "Asia",
    "subregion": "Western Asia"
  },
  {
    "alpha3Code": "TUV",
    "capital": "Funafuti",
    "name": "Tuvalu",
    "region": "Oceania",
    "subregion": "Polynesia"
  },
  {
    "alpha3Code": "TWN",
    "capital": "Taipei",
    "name": "Taiwan",
    "region": "Asia",
    "subregion": "Eastern Asia"
  },
  {
    "alpha3Code": "TZA",
    "capital": "Dodoma",
    "name": "Tanzania, United Republic of",
    "region": "Africa",
    "subregion": "Eastern Africa"
  },
  {
    "alpha3Code": "UGA",
    "capital": "Kampala",
    "name": "Uganda",
    "region": "Africa",
    "subregion": "Eastern Africa"
  },
  {
    "alpha3Code": "UKR",
    "capital": "Kyiv",
    "name": "Ukraine",
    "region": "Europe",
    "subregion": "Eastern Europe"
  },
  {
    "alpha3Code": "UMI",
    "capital": "",
    "name": "United States Minor Outlying Islands",
    "region": "Americas",
    "subregion": "Northern America"
  },
  {
    "alpha3Code": "UNK",
    "capital": "Pristina",
    "name": "Republic of Kosovo",
    "region": "Europe",
    "subregion": "Eastern Europe"
  },
  {
    "alpha3Code": "URY",
    "capital": "Montevideo",
    "name": "Uruguay",
    "region": "Americas",
    "subregion": "South America"
  },
  {
    "alpha3Code": "USA",
    "capital": "Washington, D.C.",
    "name": "United States of America",
    "region": "Americas",
    "subregion": "Northern America"
  },
  {
    "alpha3Code": "UZB",
    "capital": "Tashkent",
    "name": "Uzbekistan",
    "region": "Asia",
    "subregion": "Central Asia"
  },
  {
    "alpha3Code": "VAT",
    "capital": "Vatican City",
    "name": "Vatican City",
    "region": "Europe",
    "subregion": "Southern Europe"
  },
  {
    "alpha3Code": "VCT",
    "capital": "Kingstown",
    "name": "Saint Vincent and the Grenadines",
    "region": "Americas",
    "subregion": "Caribbean"
  },
  {
    "alpha3Code": "VEN",
    "capital": "Caracas",
    "name": "Venezuela (Bolivarian Republic of)",
    "region": "Americas",
    "subregion": "South America"
  },
  {
    "alpha3Code": "VGB",
    "capital": "Road Town",
    "name": "Virgin Islands (British)",
    "region": "Americas",
    "subregion": "Caribbean"
  },
  {
    "alpha3Code": "VIR",
    "capital": "Charlotte Amalie",
    "name": "Virgin Islands (U.S.)",
    "region": "Americas",
    "subregion": "Caribbean"
  },
  {
    "alpha3Code": "VNM",
    "capital": "Hanoi",
    "name": "Vietnam",
    "region": "Asia",
    "subregion": "South-Eastern Asia"
  },
  {
    "alpha3Code": "VUT",
    "capital": "Port Vila",
    "name": "Vanuatu",
    "region": "Oceania",
    "subregion": "Melanesia"
  },
  {
    "alpha3Code": "WLF",
    "capital": "Mata-Utu",
    "name": "Wallis and Futuna",
    "region": "Oceania",
    "subregion": "Polynesia"
  },
  {
    "alpha3Code": "WSM",
    "capital": "Apia",
    "name": "Samoa",
    "region": "Oceania",
    "subregion": "Polynesia"
  },
  {
    "alpha3Code": "YEM",
    "capital": "Sana'a",
    "name": "Yemen",
    "region": "Asia",
    "subregion": "Western Asia"
  },
  {
    "alpha3Code": "ZAF",
    "capital": "Pretoria",
    "name": "South Africa",
    "region": "Africa",
    "subregion": "Southern Africa"
  },
  {
    "alpha3Code": "ZMB",
    "capital": "Lusaka",
    "name": "Zambia",
    "region": "Africa",
    "subregion": "Eastern Africa"
  },
  {
    "alpha3Code": "ZWE",
    "capital": "Harare",
    "name": "Zimbabwe",
    "region": "Africa",
    "subregion": "Eastern Africa"
  }
]